btu/__init__.py
btu/__main__.py
btu/classroom.py
btu.py-0.0.3.dist-info/LICENSE
btu.py-0.0.3.dist-info/METADATA
btu.py-0.0.3.dist-info/WHEEL
btu.py-0.0.3.dist-info/entry_points.txt
btu.py-0.0.3.dist-info/top_level.txt
btu.py-0.0.3.dist-info/RECORD
