Metadata-Version: 2.1
Name: btu.py
Version: 0.0.3
Summary: Fetch BTU Classroom data easily
Author: Saba Umikashvili
Project-URL: Homepage, https://github.com/Graphity/btu.py
Project-URL: Bug Tracker, https://github.com/Graphity/btu.py/issues
Classifier: Programming Language :: Python :: 3
Classifier: License :: OSI Approved :: MIT License
Classifier: Operating System :: OS Independent
Requires-Python: >=3.7
License-File: LICENSE
Requires-Dist: requests
Requires-Dist: beautifulsoup4
